{"is_source_file": true, "format": "Python", "description": "A script to initialize and run a Flask web application, created by calling create_app() from the app module and starting the server on a specified port.", "external_files": ["app"], "external_methods": ["create_app"], "published": [], "classes": [], "methods": [], "calls": ["create_app", "app.run"], "search-terms": ["run.py", "create_app", "Flask", "server", "web application", "PORT environment variable"], "state": 2, "file_id": 1, "knowledge_revision": 32, "git_revision": "daeec7124a4a0770c83e8655eb2063f722ee6e84", "revision_history": [{"10": "daeec7124a4a0770c83e8655eb2063f722ee6e84"}, {"32": "daeec7124a4a0770c83e8655eb2063f722ee6e84"}], "ctags": [{"_type": "tag", "name": "app", "path": "/home/kavia/workspace/code-generation/status-tracker-application-22915-22924/status_tracker_backend/run.py", "pattern": "/^app = create_app()$/", "language": "Python", "kind": "variable"}, {"_type": "tag", "name": "port", "path": "/home/kavia/workspace/code-generation/status-tracker-application-22915-22924/status_tracker_backend/run.py", "pattern": "/^    port = int(os.getenv(\"PORT\", \"5000\"))$/", "language": "Python", "kind": "variable"}], "hash": "8c6da49aa1f9e42fd615697192616ee4", "format-version": 4, "code-base-name": "status_tracker_backend", "filename": "status_tracker_backend/run.py", "fields": [{"name": "app = create_app()", "scope": "", "scopeKind": "", "description": "unavailable"}, {"name": "port = int(os.getenv(\"PORT\", \"5000\"))", "scope": "", "scopeKind": "", "description": "unavailable"}]}